{
    "usuarios":[
        {
            "usuario":12345678,
            "contrasenia":"12ab",
            "activo": "si",
            "avatar": "http:avatar1",
            "fecha":"2019-07-30",
            "checked":false
            
        },
        {
            "usuario":87654321,
            "contrasenia":"12ab",
            "activo":"no",
            "avatar":"http:avatar2",
            "fecha":"2019-07-30",
            "checked":false

        },
        {
            "usuario":98765432,
            "contrasenia":"12ab",
            "activo": "si",
            "avatar":"http:avatar3",
            "fecha":"2019-07-30",
            "checked":false
        }
    ]
}